LICENSE.md
csnake/__init__.py
csnake/_version.py
csnake/cconstructs.py
csnake/codewriter.py
csnake/codewriterlite.py
csnake/pil_converter.py
csnake/utils.py
csnake-0.4.0.dist-info/LICENSE.md
csnake-0.4.0.dist-info/METADATA
csnake-0.4.0.dist-info/WHEEL
csnake-0.4.0.dist-info/RECORD
