Metadata-Version: 2.1
Name: csnake
Version: 0.4.0
Summary: C code generation helper package.
Home-page: https://gitlab.com/andrejr/csnake
License: MIT
Keywords: codegen,c,embedded
Author: Andrej Radović
Author-email: r.andrej@gmail.com
Requires-Python: >=3.9,<4.0
Classifier: Development Status :: 3 - Alpha
Classifier: Intended Audience :: Developers
Classifier: License :: OSI Approved :: MIT License
Classifier: Operating System :: OS Independent
Classifier: Programming Language :: C
Classifier: Programming Language :: Python
Classifier: Programming Language :: Python :: 3
Classifier: Programming Language :: Python :: 3.9
Classifier: Programming Language :: Python :: 3.10
Classifier: Programming Language :: Python :: 3.11
Classifier: Programming Language :: Python :: 3.12
Classifier: Programming Language :: Python :: 3 :: Only
Classifier: Programming Language :: Python :: 3.8
Classifier: Programming Language :: Python :: Implementation :: CPython
Classifier: Programming Language :: Python :: Implementation :: PyPy
Classifier: Topic :: Software Development :: Code Generators
Classifier: Topic :: Software Development :: Embedded Systems
Classifier: Topic :: Software Development :: Libraries :: Python Modules
Classifier: Topic :: Software Development :: Pre-processors
Provides-Extra: numpy
Provides-Extra: pillow
Provides-Extra: sympy
Requires-Dist: numpy (>=1.20) ; extra == "numpy"
Requires-Dist: pillow (>=9) ; extra == "pillow"
Requires-Dist: sympy (>=1.10) ; extra == "sympy"
Project-URL: Documentation, https://andrejr.gitlab.io/csnake/
Project-URL: Repository, https://gitlab.com/andrejr/csnake
